CHANGES.md
LICENSE
MANIFEST.in
readme.md
setup.py
example/MQTT_Zigbee_gateway.py
example/config.yaml
example/readme.md
hex/gcc_zigbee_cli_agent_router_pca10056_nrf52840_xxaa.hex
hex/gcc_zigbee_cli_agent_router_pca10059_mbr_nrf52840_xxaa.hex
hex/gcc_zigbee_cli_agent_router_pca10100_nrf52833_xxaa.hex
zb_cli_wrapper/__init__.py
zb_cli_wrapper/zb_cli_dev.py
zb_cli_wrapper.egg-info/PKG-INFO
zb_cli_wrapper.egg-info/SOURCES.txt
zb_cli_wrapper.egg-info/dependency_links.txt
zb_cli_wrapper.egg-info/requires.txt
zb_cli_wrapper.egg-info/top_level.txt
zb_cli_wrapper/nrf_dev_map/__init__.py
zb_cli_wrapper/nrf_dev_map/case_insensitive_dict.py
zb_cli_wrapper/nrf_dev_map/nrfmap.py
zb_cli_wrapper/nrf_dev_map/nrfmap_common.py
zb_cli_wrapper/nrf_dev_map/nrfmap_linux.py
zb_cli_wrapper/nrf_dev_map/nrfmap_windows.py
zb_cli_wrapper/src/__init__.py
zb_cli_wrapper/src/utils/__init__.py
zb_cli_wrapper/src/utils/communicator.py
zb_cli_wrapper/src/utils/connection.py
zb_cli_wrapper/src/utils/utils.py
zb_cli_wrapper/src/utils/cmd_wrappers/__init__.py
zb_cli_wrapper/src/utils/cmd_wrappers/base.py
zb_cli_wrapper/src/utils/cmd_wrappers/zigbee/__init__.py
zb_cli_wrapper/src/utils/cmd_wrappers/zigbee/bdb.py
zb_cli_wrapper/src/utils/cmd_wrappers/zigbee/constants.py
zb_cli_wrapper/src/utils/cmd_wrappers/zigbee/log.py
zb_cli_wrapper/src/utils/cmd_wrappers/zigbee/radio.py
zb_cli_wrapper/src/utils/cmd_wrappers/zigbee/zcl.py
zb_cli_wrapper/src/utils/cmd_wrappers/zigbee/zdo.py
zb_cli_wrapper/src/utils/zigbee_classes/__init__.py
zb_cli_wrapper/src/utils/zigbee_classes/long_address.py
zb_cli_wrapper/src/utils/zigbee_classes/clusters/__init__.py
zb_cli_wrapper/src/utils/zigbee_classes/clusters/attribute.py