Metadata-Version: 1.2
Name: zb-cli-wrapper
Version: 0.3
Summary: Nordic Semiconductor zb_cli_wrapper Python library
Home-page: https://www.nordicsemi.com
Author: Nordic Semiconductor ASA
License: 5-Clause Nordic License
Keywords: nordic nrf52840 zigbee cli_wrapper
Platform: UNKNOWN
Classifier: Development Status :: 3 - Alpha
Classifier: Intended Audience :: Developers
Classifier: Operating System :: Microsoft :: Windows
Classifier: Operating System :: POSIX :: Linux
Classifier: Topic :: System :: Networking
Classifier: Topic :: Software Development :: Embedded Systems
Classifier: License :: Other/Proprietary License
Classifier: Programming Language :: Python :: 3.7
Requires-Python: ~=3.7
